Rescore/__init__.py
Rescore/logger.py
rescpre-0.1.dist-info/METADATA
rescpre-0.1.dist-info/WHEEL
rescpre-0.1.dist-info/top_level.txt
rescpre-0.1.dist-info/RECORD
