Metadata-Version: 2.1
Name: rescpre
Version: 0.1
Summary: A custom logger library with easy color options
Home-page: https://github.com/rescore9
Author: Rescore
Author-email: admin@rescore.lol
Classifier: Programming Language :: Python :: 3
Classifier: License :: OSI Approved :: MIT License
Classifier: Operating System :: OS Independent
Requires-Python: >=3.6
